CardRotator/__init__.py
card_rotator-0.0.3.dist-info/LICENSE.txt
card_rotator-0.0.3.dist-info/METADATA
card_rotator-0.0.3.dist-info/WHEEL
card_rotator-0.0.3.dist-info/top_level.txt
card_rotator-0.0.3.dist-info/RECORD
