Metadata-Version: 2.1
Name: card-rotator
Version: 0.0.3
Summary: A simple package to generate GIF files of realistic rotating cards based on image pairs.
Author-email: Yoshi Man <yoshiman@me.com>
Project-URL: Homepage, https://github.com/yoshi-man/CardRotator
Project-URL: Bug Tracker, https://github.com/yoshi-man/CardRotator/issues
Classifier: Programming Language :: Python :: 3
Classifier: License :: OSI Approved :: MIT License
Classifier: Operating System :: OS Independent
Requires-Python: >=3.7
License-File: LICENSE.txt
